django_filters-stubs/METADATA.toml
django_filters-stubs/__init__.pyi
django_filters-stubs/compat.pyi
django_filters-stubs/conf.pyi
django_filters-stubs/constants.pyi
django_filters-stubs/exceptions.pyi
django_filters-stubs/fields.pyi
django_filters-stubs/filters.pyi
django_filters-stubs/filterset.pyi
django_filters-stubs/py.typed
django_filters-stubs/utils.pyi
django_filters-stubs/views.pyi
django_filters-stubs/widgets.pyi
django_filters-stubs/rest_framework/__init__.pyi
django_filters-stubs/rest_framework/backends.pyi
django_filters-stubs/rest_framework/filters.pyi
django_filters-stubs/rest_framework/filterset.pyi
types_django_filter-25.2.0.20251228.dist-info/licenses/LICENSE
types_django_filter-25.2.0.20251228.dist-info/METADATA
types_django_filter-25.2.0.20251228.dist-info/WHEEL
types_django_filter-25.2.0.20251228.dist-info/top_level.txt
types_django_filter-25.2.0.20251228.dist-info/RECORD
